{
  "appPageId" : "32ca75e4-69af-4463-9bec-d63daea6ef27",
  "componentName" : "siteforce:sldsOneColLayout",
  "id" : "d5826353-afc4-4558-a04d-0a5f391e765f",
  "label" : "Campaign Related List",
  "regions" : [ {
    "id" : "27b6eb38-263b-474a-86bc-fd5d9f1745fe",
    "regionName" : "header",
    "type" : "region"
  }, {
    "components" : [ {
      "componentAttributes" : {
        "customTitle" : "",
        "parentRecordId" : "{!recordId}",
        "relatedListName" : "{!relationshipApiName}",
        "showBreadCrumbs" : true,
        "showCustomTitle" : false,
        "showManualRefreshButton" : true,
        "showRowNumbers" : true
      },
      "componentName" : "forceCommunity:relatedList",
      "id" : "279074e0-415f-496c-918f-87e10a80f9cc",
      "renderPriority" : "NEUTRAL",
      "renditionMap" : { },
      "type" : "component"
    } ],
    "id" : "2a172407-b049-4c64-ab73-48a68c97828d",
    "regionName" : "content",
    "type" : "region"
  }, {
    "id" : "f8d002f0-5f50-49d3-8a7f-a578466fc8f2",
    "regionName" : "footer",
    "type" : "region"
  } ],
  "themeLayoutType" : "Inner",
  "type" : "view",
  "viewType" : "relatedlist-701"
}