{
  "appPageId" : "1b93c7b9-7173-4d34-a242-08813dbdb913",
  "componentName" : "siteforce:sldsOneColLayout",
  "id" : "04e89380-2c25-4152-93d5-5331a11e157b",
  "label" : "Record List",
  "regions" : [ {
    "id" : "613f7995-2dbe-4e29-b244-84811cfe4a65",
    "regionName" : "header",
    "type" : "region"
  }, {
    "components" : [ {
      "componentAttributes" : {
        "enableInlineEdit" : true,
        "filterName" : "{!filterId}",
        "layout" : "FULL",
        "pageSize" : 25,
        "scope" : "{!objectName}",
        "showActionBar" : true,
        "showChartsPanel" : true,
        "showDisplay" : "showall",
        "showFilterPanel" : true,
        "showImageIcon" : true,
        "showManualRefreshButton" : true,
        "showObjectName" : true,
        "showPinnedList" : true,
        "showSearchBar" : true
      },
      "componentName" : "forceCommunity:objectHome",
      "id" : "5da81df4-5c82-4a40-95f5-df3abe05c619",
      "renderPriority" : "NEUTRAL",
      "renditionMap" : { },
      "type" : "component"
    } ],
    "id" : "e963f8ed-ade4-47f0-9d42-7c53b74578f5",
    "regionName" : "content",
    "type" : "region"
  }, {
    "id" : "fbceca75-f924-4f16-a1eb-21970195807f",
    "regionName" : "footer",
    "type" : "region"
  } ],
  "themeLayoutType" : "Inner",
  "type" : "view",
  "viewType" : "list"
}