{
  "appPageId" : "1b93c7b9-7173-4d34-a242-08813dbdb913",
  "componentName" : "siteforce:sldsOneColLayout",
  "id" : "1dae5d64-6f3c-469e-942e-81ffe17efcf8",
  "label" : "User Settings",
  "regions" : [ {
    "id" : "316ff273-d4f4-4c8d-80b0-faee1d6ee8c1",
    "regionName" : "header",
    "type" : "region"
  }, {
    "components" : [ {
      "componentAttributes" : {
        "accountSectionTitle" : "Account",
        "accountTabName" : "Account Details",
        "connectedSourcesTabName" : "Connected Sources",
        "emailNotificationsTitle" : "Email Notifications",
        "emailSectionDescText" : "When email notifications are enabled, email me when someone:",
        "hideChatterNotificationSettings" : false,
        "hideConnectedSources" : false,
        "hideEmailNotificationSettings" : false,
        "hideProfileVisibilitySettings" : false,
        "id" : "{!recordId}",
        "locationTitle" : "Location",
        "profileSectionDescText" : "Customize who is able to see what on your profile page",
        "profileSectionToolTipText" : "Restricted: Visible to the employees of the company that created the site. Members: Visible to logged-in members. Public: Visible to anyone viewing pages that don't require login.",
        "profileVisibilityTitle" : "Profile Visibility",
        "settingsPageTitle" : "My Settings"
      },
      "componentName" : "forceCommunity:userSettingsCustomizable",
      "id" : "0b7a6ea3-f51f-47e2-9c6a-f06527c98e6a",
      "renderPriority" : "NEUTRAL",
      "renditionMap" : { },
      "type" : "component"
    } ],
    "id" : "af6afd40-9bab-4086-a074-c7485fbafbce",
    "regionName" : "content",
    "type" : "region"
  }, {
    "id" : "07c382c2-6204-486c-8a5b-e70be53bf3cc",
    "regionName" : "footer",
    "type" : "region"
  } ],
  "themeLayoutType" : "Inner",
  "type" : "view",
  "viewType" : "usersettings"
}